{
    "info": {
        "url_png_icon_64x64": "",
        "url_png_logo": "",
        "Website": "https://dananode.com/",
        "location": "Newburgh, IN, USA",
        "social": {
            "twitter_handle": "",
            "telegram_handle": "",
            "github_handle": "aliche123"
        },
        "about": {
            "me": "Single Pool Operator",
            "server": "servers|Core <CPU 4 core|RAM:24G|SSD:1TB hard drive + 2 Relays <CPU 4 core|RAM:24G|SSD:1TB hard drives"
    },
    "my-pool-ids": {
        "0": "52ffc8b767d55223231209643812d8de18685a4b0388ff08a7575803"
    },
    "when-satured-then-recommend": {
        "0": "small pools - support decentralization"
    }
}
}

